<?xml version="1.0" encoding="UTF-8" standalone="no"?>
<annotations>
<metadata corpusHashcode="507-16098390"/>
<unit id="TXT_IMPORTER_1492083056226">
<metadata>
<author>TXT_IMPORTER</author>
<creation-date>1492083056226</creation-date>
<lastModifier>n/a</lastModifier>
<lastModificationDate>0</lastModificationDate>
</metadata>
<characterisation>
<type>paragraph</type>
<featureSet/>
</characterisation>
<positioning>
<start>
<singlePosition index="0"/>
</start>
<end>
<singlePosition index="5"/>
</end>
</positioning>
</unit>
<unit id="TXT_IMPORTER_1492083056227">
<metadata>
<author>TXT_IMPORTER</author>
<creation-date>1492083056227</creation-date>
<lastModifier>n/a</lastModifier>
<lastModificationDate>0</lastModificationDate>
</metadata>
<characterisation>
<type>paragraph</type>
<featureSet/>
</characterisation>
<positioning>
<start>
<singlePosition index="5"/>
</start>
<end>
<singlePosition index="74"/>
</end>
</positioning>
</unit>
<unit id="TXT_IMPORTER_1492083056228">
<metadata>
<author>TXT_IMPORTER</author>
<creation-date>1492083056228</creation-date>
<lastModifier>n/a</lastModifier>
<lastModificationDate>0</lastModificationDate>
</metadata>
<characterisation>
<type>paragraph</type>
<featureSet/>
</characterisation>
<positioning>
<start>
<singlePosition index="74"/>
</start>
<end>
<singlePosition index="118"/>
</end>
</positioning>
</unit>
<unit id="TXT_IMPORTER_1492083056229">
<metadata>
<author>TXT_IMPORTER</author>
<creation-date>1492083056229</creation-date>
<lastModifier>n/a</lastModifier>
<lastModificationDate>0</lastModificationDate>
</metadata>
<characterisation>
<type>paragraph</type>
<featureSet/>
</characterisation>
<positioning>
<start>
<singlePosition index="118"/>
</start>
<end>
<singlePosition index="160"/>
</end>
</positioning>
</unit>
<unit id="TXT_IMPORTER_1492083056230">
<metadata>
<author>TXT_IMPORTER</author>
<creation-date>1492083056230</creation-date>
<lastModifier>n/a</lastModifier>
<lastModificationDate>0</lastModificationDate>
</metadata>
<characterisation>
<type>paragraph</type>
<featureSet/>
</characterisation>
<positioning>
<start>
<singlePosition index="160"/>
</start>
<end>
<singlePosition index="179"/>
</end>
</positioning>
</unit>
<unit id="TXT_IMPORTER_1492083056231">
<metadata>
<author>TXT_IMPORTER</author>
<creation-date>1492083056231</creation-date>
<lastModifier>n/a</lastModifier>
<lastModificationDate>0</lastModificationDate>
</metadata>
<characterisation>
<type>paragraph</type>
<featureSet/>
</characterisation>
<positioning>
<start>
<singlePosition index="179"/>
</start>
<end>
<singlePosition index="201"/>
</end>
</positioning>
</unit>
<unit id="TXT_IMPORTER_1492083056232">
<metadata>
<author>TXT_IMPORTER</author>
<creation-date>1492083056232</creation-date>
<lastModifier>n/a</lastModifier>
<lastModificationDate>0</lastModificationDate>
</metadata>
<characterisation>
<type>paragraph</type>
<featureSet/>
</characterisation>
<positioning>
<start>
<singlePosition index="201"/>
</start>
<end>
<singlePosition index="235"/>
</end>
</positioning>
</unit>
<unit id="TXT_IMPORTER_1492083056233">
<metadata>
<author>TXT_IMPORTER</author>
<creation-date>1492083056233</creation-date>
<lastModifier>n/a</lastModifier>
<lastModificationDate>0</lastModificationDate>
</metadata>
<characterisation>
<type>paragraph</type>
<featureSet/>
</characterisation>
<positioning>
<start>
<singlePosition index="235"/>
</start>
<end>
<singlePosition index="291"/>
</end>
</positioning>
</unit>
<unit id="TXT_IMPORTER_1492083056234">
<metadata>
<author>TXT_IMPORTER</author>
<creation-date>1492083056234</creation-date>
<lastModifier>n/a</lastModifier>
<lastModificationDate>0</lastModificationDate>
</metadata>
<characterisation>
<type>paragraph</type>
<featureSet/>
</characterisation>
<positioning>
<start>
<singlePosition index="291"/>
</start>
<end>
<singlePosition index="304"/>
</end>
</positioning>
</unit>
<unit id="TXT_IMPORTER_1492083056235">
<metadata>
<author>TXT_IMPORTER</author>
<creation-date>1492083056235</creation-date>
<lastModifier>n/a</lastModifier>
<lastModificationDate>0</lastModificationDate>
</metadata>
<characterisation>
<type>paragraph</type>
<featureSet/>
</characterisation>
<positioning>
<start>
<singlePosition index="304"/>
</start>
<end>
<singlePosition index="320"/>
</end>
</positioning>
</unit>
<unit id="TXT_IMPORTER_1492083056236">
<metadata>
<author>TXT_IMPORTER</author>
<creation-date>1492083056236</creation-date>
<lastModifier>n/a</lastModifier>
<lastModificationDate>0</lastModificationDate>
</metadata>
<characterisation>
<type>paragraph</type>
<featureSet/>
</characterisation>
<positioning>
<start>
<singlePosition index="320"/>
</start>
<end>
<singlePosition index="350"/>
</end>
</positioning>
</unit>
<unit id="TXT_IMPORTER_1492083056237">
<metadata>
<author>TXT_IMPORTER</author>
<creation-date>1492083056237</creation-date>
<lastModifier>n/a</lastModifier>
<lastModificationDate>0</lastModificationDate>
</metadata>
<characterisation>
<type>paragraph</type>
<featureSet/>
</characterisation>
<positioning>
<start>
<singlePosition index="350"/>
</start>
<end>
<singlePosition index="389"/>
</end>
</positioning>
</unit>
<unit id="TXT_IMPORTER_1492083056238">
<metadata>
<author>TXT_IMPORTER</author>
<creation-date>1492083056238</creation-date>
<lastModifier>n/a</lastModifier>
<lastModificationDate>0</lastModificationDate>
</metadata>
<characterisation>
<type>paragraph</type>
<featureSet/>
</characterisation>
<positioning>
<start>
<singlePosition index="389"/>
</start>
<end>
<singlePosition index="455"/>
</end>
</positioning>
</unit>
<unit id="TXT_IMPORTER_1492083056239">
<metadata>
<author>TXT_IMPORTER</author>
<creation-date>1492083056239</creation-date>
<lastModifier>n/a</lastModifier>
<lastModificationDate>0</lastModificationDate>
</metadata>
<characterisation>
<type>paragraph</type>
<featureSet/>
</characterisation>
<positioning>
<start>
<singlePosition index="455"/>
</start>
<end>
<singlePosition index="491"/>
</end>
</positioning>
</unit>
<unit id="TXT_IMPORTER_1492083069557">
<metadata>
<author>TXT_IMPORTER</author>
<creation-date>1492083069557</creation-date>
<lastModifier>n/a</lastModifier>
<lastModificationDate>0</lastModificationDate>
</metadata>
<characterisation>
<type>paragraph</type>
<featureSet/>
</characterisation>
<positioning>
<start>
<singlePosition index="0"/>
</start>
<end>
<singlePosition index="5"/>
</end>
</positioning>
</unit>
<unit id="TXT_IMPORTER_1492083069558">
<metadata>
<author>TXT_IMPORTER</author>
<creation-date>1492083069558</creation-date>
<lastModifier>n/a</lastModifier>
<lastModificationDate>0</lastModificationDate>
</metadata>
<characterisation>
<type>paragraph</type>
<featureSet/>
</characterisation>
<positioning>
<start>
<singlePosition index="5"/>
</start>
<end>
<singlePosition index="74"/>
</end>
</positioning>
</unit>
<unit id="TXT_IMPORTER_1492083069559">
<metadata>
<author>TXT_IMPORTER</author>
<creation-date>1492083069559</creation-date>
<lastModifier>n/a</lastModifier>
<lastModificationDate>0</lastModificationDate>
</metadata>
<characterisation>
<type>paragraph</type>
<featureSet/>
</characterisation>
<positioning>
<start>
<singlePosition index="74"/>
</start>
<end>
<singlePosition index="118"/>
</end>
</positioning>
</unit>
<unit id="TXT_IMPORTER_1492083069560">
<metadata>
<author>TXT_IMPORTER</author>
<creation-date>1492083069560</creation-date>
<lastModifier>n/a</lastModifier>
<lastModificationDate>0</lastModificationDate>
</metadata>
<characterisation>
<type>paragraph</type>
<featureSet/>
</characterisation>
<positioning>
<start>
<singlePosition index="118"/>
</start>
<end>
<singlePosition index="160"/>
</end>
</positioning>
</unit>
<unit id="TXT_IMPORTER_1492083069561">
<metadata>
<author>TXT_IMPORTER</author>
<creation-date>1492083069561</creation-date>
<lastModifier>n/a</lastModifier>
<lastModificationDate>0</lastModificationDate>
</metadata>
<characterisation>
<type>paragraph</type>
<featureSet/>
</characterisation>
<positioning>
<start>
<singlePosition index="160"/>
</start>
<end>
<singlePosition index="179"/>
</end>
</positioning>
</unit>
<unit id="TXT_IMPORTER_1492083069562">
<metadata>
<author>TXT_IMPORTER</author>
<creation-date>1492083069562</creation-date>
<lastModifier>n/a</lastModifier>
<lastModificationDate>0</lastModificationDate>
</metadata>
<characterisation>
<type>paragraph</type>
<featureSet/>
</characterisation>
<positioning>
<start>
<singlePosition index="179"/>
</start>
<end>
<singlePosition index="201"/>
</end>
</positioning>
</unit>
<unit id="TXT_IMPORTER_1492083069563">
<metadata>
<author>TXT_IMPORTER</author>
<creation-date>1492083069563</creation-date>
<lastModifier>n/a</lastModifier>
<lastModificationDate>0</lastModificationDate>
</metadata>
<characterisation>
<type>paragraph</type>
<featureSet/>
</characterisation>
<positioning>
<start>
<singlePosition index="201"/>
</start>
<end>
<singlePosition index="235"/>
</end>
</positioning>
</unit>
<unit id="TXT_IMPORTER_1492083069564">
<metadata>
<author>TXT_IMPORTER</author>
<creation-date>1492083069564</creation-date>
<lastModifier>n/a</lastModifier>
<lastModificationDate>0</lastModificationDate>
</metadata>
<characterisation>
<type>paragraph</type>
<featureSet/>
</characterisation>
<positioning>
<start>
<singlePosition index="235"/>
</start>
<end>
<singlePosition index="291"/>
</end>
</positioning>
</unit>
<unit id="TXT_IMPORTER_1492083069565">
<metadata>
<author>TXT_IMPORTER</author>
<creation-date>1492083069565</creation-date>
<lastModifier>n/a</lastModifier>
<lastModificationDate>0</lastModificationDate>
</metadata>
<characterisation>
<type>paragraph</type>
<featureSet/>
</characterisation>
<positioning>
<start>
<singlePosition index="291"/>
</start>
<end>
<singlePosition index="304"/>
</end>
</positioning>
</unit>
<unit id="TXT_IMPORTER_1492083069566">
<metadata>
<author>TXT_IMPORTER</author>
<creation-date>1492083069566</creation-date>
<lastModifier>n/a</lastModifier>
<lastModificationDate>0</lastModificationDate>
</metadata>
<characterisation>
<type>paragraph</type>
<featureSet/>
</characterisation>
<positioning>
<start>
<singlePosition index="304"/>
</start>
<end>
<singlePosition index="320"/>
</end>
</positioning>
</unit>
<unit id="TXT_IMPORTER_1492083069567">
<metadata>
<author>TXT_IMPORTER</author>
<creation-date>1492083069567</creation-date>
<lastModifier>n/a</lastModifier>
<lastModificationDate>0</lastModificationDate>
</metadata>
<characterisation>
<type>paragraph</type>
<featureSet/>
</characterisation>
<positioning>
<start>
<singlePosition index="320"/>
</start>
<end>
<singlePosition index="350"/>
</end>
</positioning>
</unit>
<unit id="TXT_IMPORTER_1492083069568">
<metadata>
<author>TXT_IMPORTER</author>
<creation-date>1492083069568</creation-date>
<lastModifier>n/a</lastModifier>
<lastModificationDate>0</lastModificationDate>
</metadata>
<characterisation>
<type>paragraph</type>
<featureSet/>
</characterisation>
<positioning>
<start>
<singlePosition index="350"/>
</start>
<end>
<singlePosition index="389"/>
</end>
</positioning>
</unit>
<unit id="TXT_IMPORTER_1492083069569">
<metadata>
<author>TXT_IMPORTER</author>
<creation-date>1492083069569</creation-date>
<lastModifier>n/a</lastModifier>
<lastModificationDate>0</lastModificationDate>
</metadata>
<characterisation>
<type>paragraph</type>
<featureSet/>
</characterisation>
<positioning>
<start>
<singlePosition index="389"/>
</start>
<end>
<singlePosition index="455"/>
</end>
</positioning>
</unit>
<unit id="TXT_IMPORTER_1492083069570">
<metadata>
<author>TXT_IMPORTER</author>
<creation-date>1492083069570</creation-date>
<lastModifier>n/a</lastModifier>
<lastModificationDate>0</lastModificationDate>
</metadata>
<characterisation>
<type>paragraph</type>
<featureSet/>
</characterisation>
<positioning>
<start>
<singlePosition index="455"/>
</start>
<end>
<singlePosition index="491"/>
</end>
</positioning>
</unit>
<unit id="vsteyer_1492083069571">
<metadata>
<author>vsteyer</author>
<creation-date>1492083069571</creation-date>
<lastModifier>n/a</lastModifier>
<lastModificationDate>0</lastModificationDate>
</metadata>
<characterisation>
<type>default</type>
<featureSet/>
</characterisation>
<positioning>
<start>
<singlePosition index="0"/>
</start>
<end>
<singlePosition index="5"/>
</end>
</positioning>
</unit>
<unit id="vsteyer_1492083069572">
<metadata>
<author>vsteyer</author>
<creation-date>1492083069572</creation-date>
<lastModifier>n/a</lastModifier>
<lastModificationDate>0</lastModificationDate>
</metadata>
<characterisation>
<type>Segment2</type>
<featureSet/>
</characterisation>
<positioning>
<start>
<singlePosition index="9"/>
</start>
<end>
<singlePosition index="74"/>
</end>
</positioning>
</unit>
<unit id="vsteyer_1492083069573">
<metadata>
<author>vsteyer</author>
<creation-date>1492083069573</creation-date>
<lastModifier>n/a</lastModifier>
<lastModificationDate>0</lastModificationDate>
</metadata>
<characterisation>
<type>Segment1</type>
<featureSet/>
</characterisation>
<positioning>
<start>
<singlePosition index="123"/>
</start>
<end>
<singlePosition index="160"/>
</end>
</positioning>
</unit>
<unit id="vsteyer_1492083069574">
<metadata>
<author>vsteyer</author>
<creation-date>1492083069574</creation-date>
<lastModifier>n/a</lastModifier>
<lastModificationDate>0</lastModificationDate>
</metadata>
<characterisation>
<type>Segment2</type>
<featureSet/>
</characterisation>
<positioning>
<start>
<singlePosition index="74"/>
</start>
<end>
<singlePosition index="118"/>
</end>
</positioning>
</unit>
<unit id="vsteyer_1492083069575">
<metadata>
<author>vsteyer</author>
<creation-date>1492083069575</creation-date>
<lastModifier>n/a</lastModifier>
<lastModificationDate>0</lastModificationDate>
</metadata>
<characterisation>
<type>Segment1</type>
<featureSet/>
</characterisation>
<positioning>
<start>
<singlePosition index="184"/>
</start>
<end>
<singlePosition index="201"/>
</end>
</positioning>
</unit>
<unit id="vsteyer_1492083069576">
<metadata>
<author>vsteyer</author>
<creation-date>1492083069576</creation-date>
<lastModifier>n/a</lastModifier>
<lastModificationDate>0</lastModificationDate>
</metadata>
<characterisation>
<type>Segment1</type>
<featureSet/>
</characterisation>
<positioning>
<start>
<singlePosition index="201"/>
</start>
<end>
<singlePosition index="235"/>
</end>
</positioning>
</unit>
<unit id="vsteyer_1492083069577">
<metadata>
<author>vsteyer</author>
<creation-date>1492083069577</creation-date>
<lastModifier>n/a</lastModifier>
<lastModificationDate>0</lastModificationDate>
</metadata>
<characterisation>
<type>Segment1</type>
<featureSet/>
</characterisation>
<positioning>
<start>
<singlePosition index="235"/>
</start>
<end>
<singlePosition index="291"/>
</end>
</positioning>
</unit>
<unit id="vsteyer_1492083069578">
<metadata>
<author>vsteyer</author>
<creation-date>1492083069578</creation-date>
<lastModifier>n/a</lastModifier>
<lastModificationDate>0</lastModificationDate>
</metadata>
<characterisation>
<type>Segment1</type>
<featureSet/>
</characterisation>
<positioning>
<start>
<singlePosition index="309"/>
</start>
<end>
<singlePosition index="320"/>
</end>
</positioning>
</unit>
<unit id="vsteyer_1492083069579">
<metadata>
<author>vsteyer</author>
<creation-date>1492083069579</creation-date>
<lastModifier>n/a</lastModifier>
<lastModificationDate>0</lastModificationDate>
</metadata>
<characterisation>
<type>Segment1</type>
<featureSet/>
</characterisation>
<positioning>
<start>
<singlePosition index="355"/>
</start>
<end>
<singlePosition index="389"/>
</end>
</positioning>
</unit>
<unit id="vsteyer_1492083069580">
<metadata>
<author>vsteyer</author>
<creation-date>1492083069580</creation-date>
<lastModifier>n/a</lastModifier>
<lastModificationDate>0</lastModificationDate>
</metadata>
<characterisation>
<type>Segment1</type>
<featureSet/>
</characterisation>
<positioning>
<start>
<singlePosition index="389"/>
</start>
<end>
<singlePosition index="455"/>
</end>
</positioning>
</unit>
<unit id="vsteyer_1492083069581">
<metadata>
<author>vsteyer</author>
<creation-date>1492083069581</creation-date>
<lastModifier>n/a</lastModifier>
<lastModificationDate>0</lastModificationDate>
</metadata>
<characterisation>
<type>Segment1</type>
<featureSet/>
</characterisation>
<positioning>
<start>
<singlePosition index="455"/>
</start>
<end>
<singlePosition index="491"/>
</end>
</positioning>
</unit>
<unit id="vsteyer_1492083069582">
<metadata>
<author>vsteyer</author>
<creation-date>1492083069582</creation-date>
<lastModifier>n/a</lastModifier>
<lastModificationDate>0</lastModificationDate>
</metadata>
<characterisation>
<type>Segment2</type>
<featureSet/>
</characterisation>
<positioning>
<start>
<singlePosition index="165"/>
</start>
<end>
<singlePosition index="179"/>
</end>
</positioning>
</unit>
<unit id="vsteyer_1492083069583">
<metadata>
<author>vsteyer</author>
<creation-date>1492083069583</creation-date>
<lastModifier>n/a</lastModifier>
<lastModificationDate>0</lastModificationDate>
</metadata>
<characterisation>
<type>Segment2</type>
<featureSet/>
</characterisation>
<positioning>
<start>
<singlePosition index="296"/>
</start>
<end>
<singlePosition index="304"/>
</end>
</positioning>
</unit>
<unit id="vsteyer_1492083069584">
<metadata>
<author>vsteyer</author>
<creation-date>1492083069584</creation-date>
<lastModifier>n/a</lastModifier>
<lastModificationDate>0</lastModificationDate>
</metadata>
<characterisation>
<type>Segment2</type>
<featureSet/>
</characterisation>
<positioning>
<start>
<singlePosition index="325"/>
</start>
<end>
<singlePosition index="350"/>
</end>
</positioning>
</unit>
<relation id="vsteyer_1492083115256">
<metadata>
<author>vsteyer</author>
<creation-date>1492083115256</creation-date>
<lastModifier>n/a</lastModifier>
<lastModificationDate>0</lastModificationDate>
</metadata>
<characterisation>
<type>Narration</type>
<featureSet/>
</characterisation>
<positioning>
<term id="vsteyer_1492083069572"/>
<term id="vsteyer_1492083069571"/>
</positioning>
</relation>
<relation id="vsteyer_1492083129495">
<metadata>
<author>vsteyer</author>
<creation-date>1492083129495</creation-date>
<lastModifier>n/a</lastModifier>
<lastModificationDate>0</lastModificationDate>
</metadata>
<characterisation>
<type>Elaboration descriptive</type>
<featureSet/>
</characterisation>
<positioning>
<term id="vsteyer_1492083069574"/>
<term id="vsteyer_1492083069572"/>
</positioning>
</relation>
<relation id="vsteyer_1492083217684">
<metadata>
<author>vsteyer</author>
<creation-date>1492083217684</creation-date>
<lastModifier>n/a</lastModifier>
<lastModificationDate>0</lastModificationDate>
</metadata>
<characterisation>
<type>Narration</type>
<featureSet/>
</characterisation>
<positioning>
<term id="vsteyer_1492083069573"/>
<term id="vsteyer_1492083069571"/>
</positioning>
</relation>
<relation id="vsteyer_1492083263602">
<metadata>
<author>vsteyer</author>
<creation-date>1492083263602</creation-date>
<lastModifier>n/a</lastModifier>
<lastModificationDate>0</lastModificationDate>
</metadata>
<characterisation>
<type>Elaboration descriptive</type>
<featureSet/>
</characterisation>
<positioning>
<term id="vsteyer_1492083069582"/>
<term id="vsteyer_1492083069573"/>
</positioning>
</relation>
<relation id="vsteyer_1492083364958">
<metadata>
<author>vsteyer</author>
<creation-date>1492083364958</creation-date>
<lastModifier>n/a</lastModifier>
<lastModificationDate>0</lastModificationDate>
</metadata>
<characterisation>
<type>Elaboration evaluative</type>
<featureSet/>
</characterisation>
<positioning>
<term id="vsteyer_1492083069575"/>
<term id="vsteyer_1492083069573"/>
</positioning>
</relation>
<relation id="vsteyer_1492083409205">
<metadata>
<author>vsteyer</author>
<creation-date>1492083409205</creation-date>
<lastModifier>n/a</lastModifier>
<lastModificationDate>0</lastModificationDate>
</metadata>
<characterisation>
<type>Conduite</type>
<featureSet/>
</characterisation>
<positioning>
<term id="vsteyer_1492083069576"/>
<term id="vsteyer_1492083069573"/>
</positioning>
</relation>
<relation id="vsteyer_1492083423517">
<metadata>
<author>vsteyer</author>
<creation-date>1492083423517</creation-date>
<lastModifier>n/a</lastModifier>
<lastModificationDate>0</lastModificationDate>
</metadata>
<characterisation>
<type>Elaboration descriptive</type>
<featureSet/>
</characterisation>
<positioning>
<term id="vsteyer_1492083069577"/>
<term id="vsteyer_1492083069576"/>
</positioning>
</relation>
<relation id="vsteyer_1492083434828">
<metadata>
<author>vsteyer</author>
<creation-date>1492083434828</creation-date>
<lastModifier>n/a</lastModifier>
<lastModificationDate>0</lastModificationDate>
</metadata>
<characterisation>
<type>Question</type>
<featureSet/>
</characterisation>
<positioning>
<term id="vsteyer_1492083069583"/>
<term id="vsteyer_1492083069577"/>
</positioning>
</relation>
<relation id="vsteyer_1492083439388">
<metadata>
<author>vsteyer</author>
<creation-date>1492083439388</creation-date>
<lastModifier>n/a</lastModifier>
<lastModificationDate>0</lastModificationDate>
</metadata>
<characterisation>
<type>Réponse</type>
<featureSet/>
</characterisation>
<positioning>
<term id="vsteyer_1492083069578"/>
<term id="vsteyer_1492083069583"/>
</positioning>
</relation>
<relation id="vsteyer_1492083479114">
<metadata>
<author>vsteyer</author>
<creation-date>1492083479114</creation-date>
<lastModifier>n/a</lastModifier>
<lastModificationDate>0</lastModificationDate>
</metadata>
<characterisation>
<type>Question</type>
<featureSet/>
</characterisation>
<positioning>
<term id="vsteyer_1492083069584"/>
<term id="vsteyer_1492083069578"/>
</positioning>
</relation>
<relation id="vsteyer_1492083482618">
<metadata>
<author>vsteyer</author>
<creation-date>1492083482618</creation-date>
<lastModifier>n/a</lastModifier>
<lastModificationDate>0</lastModificationDate>
</metadata>
<characterisation>
<type>Réponse</type>
<featureSet/>
</characterisation>
<positioning>
<term id="vsteyer_1492083069579"/>
<term id="vsteyer_1492083069584"/>
</positioning>
</relation>
<relation id="vsteyer_1492083494289">
<metadata>
<author>vsteyer</author>
<creation-date>1492083494289</creation-date>
<lastModifier>n/a</lastModifier>
<lastModificationDate>0</lastModificationDate>
</metadata>
<characterisation>
<type>Elaboration descriptive</type>
<featureSet/>
</characterisation>
<positioning>
<term id="vsteyer_1492083069580"/>
<term id="vsteyer_1492083069579"/>
</positioning>
</relation>
<relation id="vsteyer_1492083516216">
<metadata>
<author>vsteyer</author>
<creation-date>1492083516216</creation-date>
<lastModifier>n/a</lastModifier>
<lastModificationDate>0</lastModificationDate>
</metadata>
<characterisation>
<type>Elaboration prescriptive</type>
<featureSet/>
</characterisation>
<positioning>
<term id="vsteyer_1492083069581"/>
<term id="vsteyer_1492083069578"/>
</positioning>
</relation>
<flag id="vsteyer_1492083626426">
<metadata>
<author>vsteyer</author>
<creation-date>1492083626426</creation-date>
<lastModifier>n/a</lastModifier>
<lastModificationDate>0</lastModificationDate>
</metadata>
<characterisation>
<comment>florence M</comment>
</characterisation>
<positioning>
<singlePosition index="155"/>
</positioning>
</flag>
<flag id="vsteyer_1492083635874">
<metadata>
<author>vsteyer</author>
<creation-date>1492083635874</creation-date>
<lastModifier>n/a</lastModifier>
<lastModificationDate>0</lastModificationDate>
</metadata>
<characterisation>
<comment>florence R</comment>
</characterisation>
<positioning>
<singlePosition index="318"/>
</positioning>
</flag>
</annotations>
