<?xml version="1.0" encoding="UTF-8" standalone="no"?>
<annotations>
<metadata corpusHashcode="665-25307469"/>
<unit id="TXT_IMPORTER_1493048975450">
<metadata>
<author>TXT_IMPORTER</author>
<creation-date>1493048975450</creation-date>
<lastModifier>n/a</lastModifier>
<lastModificationDate>0</lastModificationDate>
</metadata>
<characterisation>
<type>paragraph</type>
<featureSet/>
</characterisation>
<positioning>
<start>
<singlePosition index="0"/>
</start>
<end>
<singlePosition index="5"/>
</end>
</positioning>
</unit>
<unit id="TXT_IMPORTER_1493048975451">
<metadata>
<author>TXT_IMPORTER</author>
<creation-date>1493048975451</creation-date>
<lastModifier>n/a</lastModifier>
<lastModificationDate>0</lastModificationDate>
</metadata>
<characterisation>
<type>paragraph</type>
<featureSet/>
</characterisation>
<positioning>
<start>
<singlePosition index="5"/>
</start>
<end>
<singlePosition index="66"/>
</end>
</positioning>
</unit>
<unit id="TXT_IMPORTER_1493048975452">
<metadata>
<author>TXT_IMPORTER</author>
<creation-date>1493048975452</creation-date>
<lastModifier>n/a</lastModifier>
<lastModificationDate>0</lastModificationDate>
</metadata>
<characterisation>
<type>paragraph</type>
<featureSet/>
</characterisation>
<positioning>
<start>
<singlePosition index="66"/>
</start>
<end>
<singlePosition index="80"/>
</end>
</positioning>
</unit>
<unit id="TXT_IMPORTER_1493048975453">
<metadata>
<author>TXT_IMPORTER</author>
<creation-date>1493048975453</creation-date>
<lastModifier>n/a</lastModifier>
<lastModificationDate>0</lastModificationDate>
</metadata>
<characterisation>
<type>paragraph</type>
<featureSet/>
</characterisation>
<positioning>
<start>
<singlePosition index="80"/>
</start>
<end>
<singlePosition index="169"/>
</end>
</positioning>
</unit>
<unit id="TXT_IMPORTER_1493048975454">
<metadata>
<author>TXT_IMPORTER</author>
<creation-date>1493048975454</creation-date>
<lastModifier>n/a</lastModifier>
<lastModificationDate>0</lastModificationDate>
</metadata>
<characterisation>
<type>paragraph</type>
<featureSet/>
</characterisation>
<positioning>
<start>
<singlePosition index="169"/>
</start>
<end>
<singlePosition index="264"/>
</end>
</positioning>
</unit>
<unit id="TXT_IMPORTER_1493048975455">
<metadata>
<author>TXT_IMPORTER</author>
<creation-date>1493048975455</creation-date>
<lastModifier>n/a</lastModifier>
<lastModificationDate>0</lastModificationDate>
</metadata>
<characterisation>
<type>paragraph</type>
<featureSet/>
</characterisation>
<positioning>
<start>
<singlePosition index="264"/>
</start>
<end>
<singlePosition index="292"/>
</end>
</positioning>
</unit>
<unit id="TXT_IMPORTER_1493048975456">
<metadata>
<author>TXT_IMPORTER</author>
<creation-date>1493048975456</creation-date>
<lastModifier>n/a</lastModifier>
<lastModificationDate>0</lastModificationDate>
</metadata>
<characterisation>
<type>paragraph</type>
<featureSet/>
</characterisation>
<positioning>
<start>
<singlePosition index="292"/>
</start>
<end>
<singlePosition index="306"/>
</end>
</positioning>
</unit>
<unit id="TXT_IMPORTER_1493048975457">
<metadata>
<author>TXT_IMPORTER</author>
<creation-date>1493048975457</creation-date>
<lastModifier>n/a</lastModifier>
<lastModificationDate>0</lastModificationDate>
</metadata>
<characterisation>
<type>paragraph</type>
<featureSet/>
</characterisation>
<positioning>
<start>
<singlePosition index="306"/>
</start>
<end>
<singlePosition index="392"/>
</end>
</positioning>
</unit>
<unit id="TXT_IMPORTER_1493048975458">
<metadata>
<author>TXT_IMPORTER</author>
<creation-date>1493048975458</creation-date>
<lastModifier>n/a</lastModifier>
<lastModificationDate>0</lastModificationDate>
</metadata>
<characterisation>
<type>paragraph</type>
<featureSet/>
</characterisation>
<positioning>
<start>
<singlePosition index="392"/>
</start>
<end>
<singlePosition index="404"/>
</end>
</positioning>
</unit>
<unit id="TXT_IMPORTER_1493048975459">
<metadata>
<author>TXT_IMPORTER</author>
<creation-date>1493048975459</creation-date>
<lastModifier>n/a</lastModifier>
<lastModificationDate>0</lastModificationDate>
</metadata>
<characterisation>
<type>paragraph</type>
<featureSet/>
</characterisation>
<positioning>
<start>
<singlePosition index="404"/>
</start>
<end>
<singlePosition index="503"/>
</end>
</positioning>
</unit>
<unit id="TXT_IMPORTER_1493048975460">
<metadata>
<author>TXT_IMPORTER</author>
<creation-date>1493048975460</creation-date>
<lastModifier>n/a</lastModifier>
<lastModificationDate>0</lastModificationDate>
</metadata>
<characterisation>
<type>paragraph</type>
<featureSet/>
</characterisation>
<positioning>
<start>
<singlePosition index="503"/>
</start>
<end>
<singlePosition index="550"/>
</end>
</positioning>
</unit>
<unit id="TXT_IMPORTER_1493048975461">
<metadata>
<author>TXT_IMPORTER</author>
<creation-date>1493048975461</creation-date>
<lastModifier>n/a</lastModifier>
<lastModificationDate>0</lastModificationDate>
</metadata>
<characterisation>
<type>paragraph</type>
<featureSet/>
</characterisation>
<positioning>
<start>
<singlePosition index="550"/>
</start>
<end>
<singlePosition index="608"/>
</end>
</positioning>
</unit>
<unit id="TXT_IMPORTER_1493048975462">
<metadata>
<author>TXT_IMPORTER</author>
<creation-date>1493048975462</creation-date>
<lastModifier>n/a</lastModifier>
<lastModificationDate>0</lastModificationDate>
</metadata>
<characterisation>
<type>paragraph</type>
<featureSet/>
</characterisation>
<positioning>
<start>
<singlePosition index="608"/>
</start>
<end>
<singlePosition index="643"/>
</end>
</positioning>
</unit>
<unit id="TXT_IMPORTER_1493048988122">
<metadata>
<author>TXT_IMPORTER</author>
<creation-date>1493048988122</creation-date>
<lastModifier>n/a</lastModifier>
<lastModificationDate>0</lastModificationDate>
</metadata>
<characterisation>
<type>paragraph</type>
<featureSet/>
</characterisation>
<positioning>
<start>
<singlePosition index="0"/>
</start>
<end>
<singlePosition index="5"/>
</end>
</positioning>
</unit>
<unit id="TXT_IMPORTER_1493048988123">
<metadata>
<author>TXT_IMPORTER</author>
<creation-date>1493048988123</creation-date>
<lastModifier>n/a</lastModifier>
<lastModificationDate>0</lastModificationDate>
</metadata>
<characterisation>
<type>paragraph</type>
<featureSet/>
</characterisation>
<positioning>
<start>
<singlePosition index="5"/>
</start>
<end>
<singlePosition index="66"/>
</end>
</positioning>
</unit>
<unit id="TXT_IMPORTER_1493048988124">
<metadata>
<author>TXT_IMPORTER</author>
<creation-date>1493048988124</creation-date>
<lastModifier>n/a</lastModifier>
<lastModificationDate>0</lastModificationDate>
</metadata>
<characterisation>
<type>paragraph</type>
<featureSet/>
</characterisation>
<positioning>
<start>
<singlePosition index="66"/>
</start>
<end>
<singlePosition index="80"/>
</end>
</positioning>
</unit>
<unit id="TXT_IMPORTER_1493048988125">
<metadata>
<author>TXT_IMPORTER</author>
<creation-date>1493048988125</creation-date>
<lastModifier>n/a</lastModifier>
<lastModificationDate>0</lastModificationDate>
</metadata>
<characterisation>
<type>paragraph</type>
<featureSet/>
</characterisation>
<positioning>
<start>
<singlePosition index="80"/>
</start>
<end>
<singlePosition index="169"/>
</end>
</positioning>
</unit>
<unit id="TXT_IMPORTER_1493048988126">
<metadata>
<author>TXT_IMPORTER</author>
<creation-date>1493048988126</creation-date>
<lastModifier>n/a</lastModifier>
<lastModificationDate>0</lastModificationDate>
</metadata>
<characterisation>
<type>paragraph</type>
<featureSet/>
</characterisation>
<positioning>
<start>
<singlePosition index="169"/>
</start>
<end>
<singlePosition index="264"/>
</end>
</positioning>
</unit>
<unit id="TXT_IMPORTER_1493048988127">
<metadata>
<author>TXT_IMPORTER</author>
<creation-date>1493048988127</creation-date>
<lastModifier>n/a</lastModifier>
<lastModificationDate>0</lastModificationDate>
</metadata>
<characterisation>
<type>paragraph</type>
<featureSet/>
</characterisation>
<positioning>
<start>
<singlePosition index="264"/>
</start>
<end>
<singlePosition index="292"/>
</end>
</positioning>
</unit>
<unit id="TXT_IMPORTER_1493048988128">
<metadata>
<author>TXT_IMPORTER</author>
<creation-date>1493048988128</creation-date>
<lastModifier>n/a</lastModifier>
<lastModificationDate>0</lastModificationDate>
</metadata>
<characterisation>
<type>paragraph</type>
<featureSet/>
</characterisation>
<positioning>
<start>
<singlePosition index="292"/>
</start>
<end>
<singlePosition index="306"/>
</end>
</positioning>
</unit>
<unit id="TXT_IMPORTER_1493048988129">
<metadata>
<author>TXT_IMPORTER</author>
<creation-date>1493048988129</creation-date>
<lastModifier>n/a</lastModifier>
<lastModificationDate>0</lastModificationDate>
</metadata>
<characterisation>
<type>paragraph</type>
<featureSet/>
</characterisation>
<positioning>
<start>
<singlePosition index="306"/>
</start>
<end>
<singlePosition index="392"/>
</end>
</positioning>
</unit>
<unit id="TXT_IMPORTER_1493048988130">
<metadata>
<author>TXT_IMPORTER</author>
<creation-date>1493048988130</creation-date>
<lastModifier>n/a</lastModifier>
<lastModificationDate>0</lastModificationDate>
</metadata>
<characterisation>
<type>paragraph</type>
<featureSet/>
</characterisation>
<positioning>
<start>
<singlePosition index="392"/>
</start>
<end>
<singlePosition index="404"/>
</end>
</positioning>
</unit>
<unit id="TXT_IMPORTER_1493048988131">
<metadata>
<author>TXT_IMPORTER</author>
<creation-date>1493048988131</creation-date>
<lastModifier>n/a</lastModifier>
<lastModificationDate>0</lastModificationDate>
</metadata>
<characterisation>
<type>paragraph</type>
<featureSet/>
</characterisation>
<positioning>
<start>
<singlePosition index="404"/>
</start>
<end>
<singlePosition index="503"/>
</end>
</positioning>
</unit>
<unit id="TXT_IMPORTER_1493048988132">
<metadata>
<author>TXT_IMPORTER</author>
<creation-date>1493048988132</creation-date>
<lastModifier>n/a</lastModifier>
<lastModificationDate>0</lastModificationDate>
</metadata>
<characterisation>
<type>paragraph</type>
<featureSet/>
</characterisation>
<positioning>
<start>
<singlePosition index="503"/>
</start>
<end>
<singlePosition index="550"/>
</end>
</positioning>
</unit>
<unit id="TXT_IMPORTER_1493048988133">
<metadata>
<author>TXT_IMPORTER</author>
<creation-date>1493048988133</creation-date>
<lastModifier>n/a</lastModifier>
<lastModificationDate>0</lastModificationDate>
</metadata>
<characterisation>
<type>paragraph</type>
<featureSet/>
</characterisation>
<positioning>
<start>
<singlePosition index="550"/>
</start>
<end>
<singlePosition index="608"/>
</end>
</positioning>
</unit>
<unit id="TXT_IMPORTER_1493048988134">
<metadata>
<author>TXT_IMPORTER</author>
<creation-date>1493048988134</creation-date>
<lastModifier>n/a</lastModifier>
<lastModificationDate>0</lastModificationDate>
</metadata>
<characterisation>
<type>paragraph</type>
<featureSet/>
</characterisation>
<positioning>
<start>
<singlePosition index="608"/>
</start>
<end>
<singlePosition index="643"/>
</end>
</positioning>
</unit>
<unit id="vsteyer_1493048988135">
<metadata>
<author>vsteyer</author>
<creation-date>1493048988135</creation-date>
<lastModifier>n/a</lastModifier>
<lastModificationDate>0</lastModificationDate>
</metadata>
<characterisation>
<type>Segment1</type>
<featureSet/>
</characterisation>
<positioning>
<start>
<singlePosition index="0"/>
</start>
<end>
<singlePosition index="5"/>
</end>
</positioning>
</unit>
<unit id="vsteyer_1493048988136">
<metadata>
<author>vsteyer</author>
<creation-date>1493048988136</creation-date>
<lastModifier>n/a</lastModifier>
<lastModificationDate>0</lastModificationDate>
</metadata>
<characterisation>
<type>Segment1</type>
<featureSet/>
</characterisation>
<positioning>
<start>
<singlePosition index="72"/>
</start>
<end>
<singlePosition index="80"/>
</end>
</positioning>
</unit>
<unit id="vsteyer_1493048988137">
<metadata>
<author>vsteyer</author>
<creation-date>1493048988137</creation-date>
<lastModifier>n/a</lastModifier>
<lastModificationDate>0</lastModificationDate>
</metadata>
<characterisation>
<type>Segment1</type>
<featureSet/>
</characterisation>
<positioning>
<start>
<singlePosition index="298"/>
</start>
<end>
<singlePosition index="306"/>
</end>
</positioning>
</unit>
<unit id="vsteyer_1493048988138">
<metadata>
<author>vsteyer</author>
<creation-date>1493048988138</creation-date>
<lastModifier>n/a</lastModifier>
<lastModificationDate>0</lastModificationDate>
</metadata>
<characterisation>
<type>Segment1</type>
<featureSet/>
</characterisation>
<positioning>
<start>
<singlePosition index="398"/>
</start>
<end>
<singlePosition index="404"/>
</end>
</positioning>
</unit>
<unit id="vsteyer_1493048988139">
<metadata>
<author>vsteyer</author>
<creation-date>1493048988139</creation-date>
<lastModifier>n/a</lastModifier>
<lastModificationDate>0</lastModificationDate>
</metadata>
<characterisation>
<type>Segment2</type>
<featureSet/>
</characterisation>
<positioning>
<start>
<singlePosition index="11"/>
</start>
<end>
<singlePosition index="66"/>
</end>
</positioning>
</unit>
<unit id="vsteyer_1493048988140">
<metadata>
<author>vsteyer</author>
<creation-date>1493048988140</creation-date>
<lastModifier>n/a</lastModifier>
<lastModificationDate>0</lastModificationDate>
</metadata>
<characterisation>
<type>Segment2</type>
<featureSet/>
</characterisation>
<positioning>
<start>
<singlePosition index="86"/>
</start>
<end>
<singlePosition index="169"/>
</end>
</positioning>
</unit>
<unit id="vsteyer_1493048988141">
<metadata>
<author>vsteyer</author>
<creation-date>1493048988141</creation-date>
<lastModifier>n/a</lastModifier>
<lastModificationDate>0</lastModificationDate>
</metadata>
<characterisation>
<type>Segment2</type>
<featureSet/>
</characterisation>
<positioning>
<start>
<singlePosition index="169"/>
</start>
<end>
<singlePosition index="264"/>
</end>
</positioning>
</unit>
<unit id="vsteyer_1493048988142">
<metadata>
<author>vsteyer</author>
<creation-date>1493048988142</creation-date>
<lastModifier>n/a</lastModifier>
<lastModificationDate>0</lastModificationDate>
</metadata>
<characterisation>
<type>Segment2</type>
<featureSet/>
</characterisation>
<positioning>
<start>
<singlePosition index="264"/>
</start>
<end>
<singlePosition index="292"/>
</end>
</positioning>
</unit>
<unit id="vsteyer_1493048988143">
<metadata>
<author>vsteyer</author>
<creation-date>1493048988143</creation-date>
<lastModifier>n/a</lastModifier>
<lastModificationDate>0</lastModificationDate>
</metadata>
<characterisation>
<type>Segment2</type>
<featureSet/>
</characterisation>
<positioning>
<start>
<singlePosition index="312"/>
</start>
<end>
<singlePosition index="392"/>
</end>
</positioning>
</unit>
<unit id="vsteyer_1493048988144">
<metadata>
<author>vsteyer</author>
<creation-date>1493048988144</creation-date>
<lastModifier>n/a</lastModifier>
<lastModificationDate>0</lastModificationDate>
</metadata>
<characterisation>
<type>Segment2</type>
<featureSet/>
</characterisation>
<positioning>
<start>
<singlePosition index="410"/>
</start>
<end>
<singlePosition index="503"/>
</end>
</positioning>
</unit>
<unit id="vsteyer_1493048988145">
<metadata>
<author>vsteyer</author>
<creation-date>1493048988145</creation-date>
<lastModifier>n/a</lastModifier>
<lastModificationDate>0</lastModificationDate>
</metadata>
<characterisation>
<type>Segment2</type>
<featureSet/>
</characterisation>
<positioning>
<start>
<singlePosition index="503"/>
</start>
<end>
<singlePosition index="550"/>
</end>
</positioning>
</unit>
<unit id="vsteyer_1493048988146">
<metadata>
<author>vsteyer</author>
<creation-date>1493048988146</creation-date>
<lastModifier>n/a</lastModifier>
<lastModificationDate>0</lastModificationDate>
</metadata>
<characterisation>
<type>Segment2</type>
<featureSet/>
</characterisation>
<positioning>
<start>
<singlePosition index="550"/>
</start>
<end>
<singlePosition index="608"/>
</end>
</positioning>
</unit>
<unit id="vsteyer_1493048988147">
<metadata>
<author>vsteyer</author>
<creation-date>1493048988147</creation-date>
<lastModifier>n/a</lastModifier>
<lastModificationDate>0</lastModificationDate>
</metadata>
<characterisation>
<type>Segment2</type>
<featureSet/>
</characterisation>
<positioning>
<start>
<singlePosition index="608"/>
</start>
<end>
<singlePosition index="643"/>
</end>
</positioning>
</unit>
<relation id="vsteyer_1493049007755">
<metadata>
<author>vsteyer</author>
<creation-date>1493049007755</creation-date>
<lastModifier>n/a</lastModifier>
<lastModificationDate>0</lastModificationDate>
</metadata>
<characterisation>
<type>Phatique</type>
<featureSet/>
</characterisation>
<positioning>
<term id="vsteyer_1493048988136"/>
<term id="vsteyer_1493048988139"/>
</positioning>
</relation>
<relation id="vsteyer_1493049026789">
<metadata>
<author>vsteyer</author>
<creation-date>1493049026789</creation-date>
<lastModifier>n/a</lastModifier>
<lastModificationDate>0</lastModificationDate>
</metadata>
<characterisation>
<type>Elaboration descriptive</type>
<featureSet/>
</characterisation>
<positioning>
<term id="vsteyer_1493048988141"/>
<term id="vsteyer_1493048988140"/>
</positioning>
</relation>
<relation id="vsteyer_1493049038740">
<metadata>
<author>vsteyer</author>
<creation-date>1493049038740</creation-date>
<lastModifier>n/a</lastModifier>
<lastModificationDate>0</lastModificationDate>
</metadata>
<characterisation>
<type>Narration</type>
<featureSet/>
</characterisation>
<positioning>
<term id="vsteyer_1493048988142"/>
<term id="vsteyer_1493048988141"/>
</positioning>
</relation>
<relation id="vsteyer_1493049049796">
<metadata>
<author>vsteyer</author>
<creation-date>1493049049796</creation-date>
<lastModifier>n/a</lastModifier>
<lastModificationDate>0</lastModificationDate>
</metadata>
<characterisation>
<type>Phatique</type>
<featureSet/>
</characterisation>
<positioning>
<term id="vsteyer_1493048988137"/>
<term id="vsteyer_1493048988142"/>
</positioning>
</relation>
<relation id="vsteyer_1493049062860">
<metadata>
<author>vsteyer</author>
<creation-date>1493049062860</creation-date>
<lastModifier>n/a</lastModifier>
<lastModificationDate>0</lastModificationDate>
</metadata>
<characterisation>
<type>Elaboration descriptive</type>
<featureSet/>
</characterisation>
<positioning>
<term id="vsteyer_1493048988140"/>
<term id="vsteyer_1493048988139"/>
</positioning>
</relation>
<relation id="vsteyer_1493049076755">
<metadata>
<author>vsteyer</author>
<creation-date>1493049076755</creation-date>
<lastModifier>n/a</lastModifier>
<lastModificationDate>0</lastModificationDate>
</metadata>
<characterisation>
<type>Elaboration descriptive</type>
<featureSet/>
</characterisation>
<positioning>
<term id="vsteyer_1493048988143"/>
<term id="vsteyer_1493048988142"/>
</positioning>
</relation>
<relation id="vsteyer_1493049081019">
<metadata>
<author>vsteyer</author>
<creation-date>1493049081019</creation-date>
<lastModifier>n/a</lastModifier>
<lastModificationDate>0</lastModificationDate>
</metadata>
<characterisation>
<type>Elaboration descriptive</type>
<featureSet/>
</characterisation>
<positioning>
<term id="vsteyer_1493048988138"/>
<term id="vsteyer_1493048988143"/>
</positioning>
</relation>
<relation id="vsteyer_1493049091531">
<metadata>
<author>vsteyer</author>
<creation-date>1493049091531</creation-date>
<lastModifier>n/a</lastModifier>
<lastModificationDate>0</lastModificationDate>
</metadata>
<characterisation>
<type>Elaboration descriptive</type>
<featureSet/>
</characterisation>
<positioning>
<term id="vsteyer_1493048988144"/>
<term id="vsteyer_1493048988143"/>
</positioning>
</relation>
<relation id="vsteyer_1493049097586">
<metadata>
<author>vsteyer</author>
<creation-date>1493049097586</creation-date>
<lastModifier>n/a</lastModifier>
<lastModificationDate>0</lastModificationDate>
</metadata>
<characterisation>
<type>Elaboration descriptive</type>
<featureSet/>
</characterisation>
<positioning>
<term id="vsteyer_1493048988145"/>
<term id="vsteyer_1493048988144"/>
</positioning>
</relation>
<relation id="vsteyer_1493049098795">
<metadata>
<author>vsteyer</author>
<creation-date>1493049098795</creation-date>
<lastModifier>n/a</lastModifier>
<lastModificationDate>0</lastModificationDate>
</metadata>
<characterisation>
<type>Elaboration descriptive</type>
<featureSet/>
</characterisation>
<positioning>
<term id="vsteyer_1493048988146"/>
<term id="vsteyer_1493048988145"/>
</positioning>
</relation>
<relation id="vsteyer_1493049099931">
<metadata>
<author>vsteyer</author>
<creation-date>1493049099931</creation-date>
<lastModifier>n/a</lastModifier>
<lastModificationDate>0</lastModificationDate>
</metadata>
<characterisation>
<type>Elaboration descriptive</type>
<featureSet/>
</characterisation>
<positioning>
<term id="vsteyer_1493048988147"/>
<term id="vsteyer_1493048988146"/>
</positioning>
</relation>
<flag id="vsteyer_1493049119512">
<metadata>
<author>vsteyer</author>
<creation-date>1493049119512</creation-date>
<lastModifier>n/a</lastModifier>
<lastModificationDate>0</lastModificationDate>
</metadata>
<characterisation>
<comment>Etudes</comment>
</characterisation>
<positioning>
<singlePosition index="11"/>
</positioning>
</flag>
</annotations>
